macdict/__init__.py
macdict/cli.py
macdict/dictionary.py
macdict/foundation.py
macdict-0.1.4.dist-info/LICENSE
macdict-0.1.4.dist-info/METADATA
macdict-0.1.4.dist-info/WHEEL
macdict-0.1.4.dist-info/entry_points.txt
macdict-0.1.4.dist-info/top_level.txt
macdict-0.1.4.dist-info/RECORD
