Metadata-Version: 2.1
Name: macdict
Version: 0.1.4
Summary: CLI and library to look up dictionary in macOS.
Home-page: https://github.com/tonyseek/macdict
Author: Jiangge Zhang
Author-email: tonyseek@gmail.com
License: MIT
Keywords: Dictionary.app
Platform: darwin
Classifier: Development Status :: 3 - Alpha
Classifier: Environment :: Console
Classifier: Environment :: MacOS X
Classifier: License :: OSI Approved :: MIT License
Classifier: Operating System :: MacOS
Classifier: Operating System :: MacOS :: MacOS X
Classifier: Programming Language :: Python :: 2.7
Classifier: Programming Language :: Python :: 3.3
Classifier: Programming Language :: Python :: 3.4
Classifier: Programming Language :: Python :: 3.5
Classifier: Programming Language :: Python :: 3.6
Classifier: Programming Language :: Python :: Implementation :: CPython
Classifier: Programming Language :: Python :: Implementation :: PyPy
Classifier: Topic :: Education
Classifier: Topic :: Utilities
